<annotation>
	<folder>pics</folder>
	<filename>056.JPG</filename>
	<path>/home/seniordesign/Desktop/SeniorDesign/pics/056.JPG</path>
	<source>
		<database>Unknown</database>
	</source>
	<size>
		<width>4032</width>
		<height>3024</height>
		<depth>3</depth>
	</size>
	<segmented>0</segmented>
	<object>
		<name>bolt</name>
		<pose>Unspecified</pose>
		<truncated>0</truncated>
		<difficult>0</difficult>
		<bndbox>
			<xmin>1906</xmin>
			<ymin>56</ymin>
			<xmax>2201</xmax>
			<ymax>371</ymax>
		</bndbox>
	</object>
	<object>
		<name>bolt</name>
		<pose>Unspecified</pose>
		<truncated>0</truncated>
		<difficult>0</difficult>
		<bndbox>
			<xmin>2735</xmin>
			<ymin>190</ymin>
			<xmax>3035</xmax>
			<ymax>494</ymax>
		</bndbox>
	</object>
	<object>
		<name>bolt</name>
		<pose>Unspecified</pose>
		<truncated>0</truncated>
		<difficult>0</difficult>
		<bndbox>
			<xmin>2206</xmin>
			<ymin>875</ymin>
			<xmax>2487</xmax>
			<ymax>1152</ymax>
		</bndbox>
	</object>
</annotation>
