<annotation>
	<folder>pics</folder>
	<filename>061.JPG</filename>
	<path>/home/seniordesign/Desktop/SeniorDesign/pics/061.JPG</path>
	<source>
		<database>Unknown</database>
	</source>
	<size>
		<width>4032</width>
		<height>3024</height>
		<depth>3</depth>
	</size>
	<segmented>0</segmented>
	<object>
		<name>bolt</name>
		<pose>Unspecified</pose>
		<truncated>0</truncated>
		<difficult>0</difficult>
		<bndbox>
			<xmin>663</xmin>
			<ymin>461</ymin>
			<xmax>1030</xmax>
			<ymax>828</ymax>
		</bndbox>
	</object>
	<object>
		<name>bolt</name>
		<pose>Unspecified</pose>
		<truncated>0</truncated>
		<difficult>0</difficult>
		<bndbox>
			<xmin>1701</xmin>
			<ymin>547</ymin>
			<xmax>2058</xmax>
			<ymax>913</ymax>
		</bndbox>
	</object>
	<object>
		<name>bolt</name>
		<pose>Unspecified</pose>
		<truncated>0</truncated>
		<difficult>0</difficult>
		<bndbox>
			<xmin>1187</xmin>
			<ymin>1390</ymin>
			<xmax>1535</xmax>
			<ymax>1709</ymax>
		</bndbox>
	</object>
</annotation>
